tidal_dl_ng/__init__.py
tidal_dl_ng/api.py
tidal_dl_ng/cli.py
tidal_dl_ng/config.py
tidal_dl_ng/constants.py
tidal_dl_ng/dialog.py
tidal_dl_ng/download.py
tidal_dl_ng/gui.py
tidal_dl_ng/helper/__init__.py
tidal_dl_ng/helper/camelot.py
tidal_dl_ng/helper/cli.py
tidal_dl_ng/helper/decorator.py
tidal_dl_ng/helper/decryption.py
tidal_dl_ng/helper/exceptions.py
tidal_dl_ng/helper/gui.py
tidal_dl_ng/helper/path.py
tidal_dl_ng/helper/tidal.py
tidal_dl_ng/helper/wrapper.py
tidal_dl_ng/logger.py
tidal_dl_ng/metadata.py
tidal_dl_ng/model/__init__.py
tidal_dl_ng/model/cfg.py
tidal_dl_ng/model/downloader.py
tidal_dl_ng/model/gui_data.py
tidal_dl_ng/model/meta.py
tidal_dl_ng/ui/__init__.py
tidal_dl_ng/ui/default_album_image.png
tidal_dl_ng/ui/dialog_login.py
tidal_dl_ng/ui/dialog_login.ui
tidal_dl_ng/ui/dialog_settings.py
tidal_dl_ng/ui/dialog_settings.ui
tidal_dl_ng/ui/dialog_version.py
tidal_dl_ng/ui/dialog_version.ui
tidal_dl_ng/ui/dummy_register.py
tidal_dl_ng/ui/dummy_wiggly.py
tidal_dl_ng/ui/icon.icns
tidal_dl_ng/ui/icon.ico
tidal_dl_ng/ui/icon16.png
tidal_dl_ng/ui/icon256.png
tidal_dl_ng/ui/icon32.png
tidal_dl_ng/ui/icon48.png
tidal_dl_ng/ui/icon512.png
tidal_dl_ng/ui/icon64.png
tidal_dl_ng/ui/main.py
tidal_dl_ng/ui/main.ui
tidal_dl_ng/ui/spinner.py
tidal_dl_ng/worker.py
tidal_dl_ng-0.33.0.dist-info/METADATA
tidal_dl_ng-0.33.0.dist-info/WHEEL
tidal_dl_ng-0.33.0.dist-info/entry_points.txt
tidal_dl_ng-0.33.0.dist-info/licenses/LICENSE
tidal_dl_ng-0.33.0.dist-info/RECORD
